async_sqlmodel/__init__.py
async_sqlmodel/main.py
async_sqlmodel/py.typed
async_sqlmodel-0.1.3.dist-info/LICENSE
async_sqlmodel-0.1.3.dist-info/METADATA
async_sqlmodel-0.1.3.dist-info/WHEEL
async_sqlmodel-0.1.3.dist-info/RECORD
