Metadata-Version: 2.1
Name: async-sqlmodel
Version: 0.1.3
Summary: 
Author: 2jun0
Author-email: soo28819@gmail.com
Requires-Python: >=3.7,<4.0
Classifier: Programming Language :: Python :: 3
Classifier: Programming Language :: Python :: 3.7
Classifier: Programming Language :: Python :: 3.8
Classifier: Programming Language :: Python :: 3.9
Classifier: Programming Language :: Python :: 3.10
Classifier: Programming Language :: Python :: 3.11
Classifier: Programming Language :: Python :: 3.12
Requires-Dist: greenlet (>=3.0.3,<4.0.0)
Requires-Dist: sqlalchemy (>=2.0.29,<3.0.0)
Requires-Dist: sqlmodel (>=0.0.16,<0.0.17)
